MANIFEST.in
readme.rst
setup.py
django_radagast.egg-info/PKG-INFO
django_radagast.egg-info/SOURCES.txt
django_radagast.egg-info/dependency_links.txt
django_radagast.egg-info/top_level.txt
django_radagast.egg-info/zip-safe
radagast/__init__.py
radagast/models.py
radagast/test_urls.py
radagast/test_views.py
radagast/tests.py
radagast/wizard.py