Metadata-Version: 1.0
Name: django-radagast
Version: 0.3
Summary: The other wizard
Home-page: http://mozilla.com
Author: Mozilla
Author-email: andym@mozilla.com
License: BSD
Platform: UNKNOWN
Classifier: Programming Language :: Python
Classifier: Topic :: Software Development :: Libraries :: Python Modules
Classifier: Environment :: Web Environment :: Mozilla
Classifier: Framework :: Django
